nonebot_plugin_sunsetbot/__init__.py
nonebot_plugin_sunsetbot/config.py
nonebot_plugin_sunsetbot/db.py
nonebot_plugin_sunsetbot/db2.py
nonebot_plugin_sunsetbot/handler.py
nonebot_plugin_sunsetbot/sunsetbot.py
nonebot_plugin_sunsetbot-0.2.0.dist-info/METADATA
nonebot_plugin_sunsetbot-0.2.0.dist-info/WHEEL
nonebot_plugin_sunsetbot-0.2.0.dist-info/RECORD
