Metadata-Version: 2.1
Name: nonebot-plugin-sunsetbot
Version: 0.2.0
Summary: SunsetBot朝霞晚霞查询
Home-page: https://github.com/MichiyamaKaren/nonebot-plugin-sunsetbot
Author: MichiyamaKaren
Author-email: mustarfar@163.com
Requires-Python: >=3.12,<4.0
Classifier: Programming Language :: Python :: 3
Classifier: Programming Language :: Python :: 3.12
Classifier: Programming Language :: Python :: 3.13
Requires-Dist: aiohttp (>=3.11.11,<4.0.0)
Requires-Dist: aiosqlite (>=0.20.0,<0.21.0)
Requires-Dist: nonebot-adapter-console (>=0.6.0,<0.7.0)
Requires-Dist: nonebot-adapter-onebot (>=2.4.6,<3.0.0)
Requires-Dist: nonebot-plugin-apscheduler (>=0.5.0,<0.6.0)
Requires-Dist: nonebot-plugin-localstore (>=0.7.3,<0.8.0)
Requires-Dist: nonebot2[fastapi] (>=2.4.1,<3.0.0)
